tinyusdz/usd_saver.py
tinyusdz/tydra.py
tinyusdz/ctinyusd.py
tinyusdz/prims.py
tinyusdz/version.py
tinyusdz/__init__.py
tinyusdz/usd_loader.py
tinyusdz/compat_typing_extensions.py
tinyusdz-0.8.0rc6.data/data/tinyusdz/libc-tinyusd.so
tinyusdz-0.8.0rc6.dist-info/WHEEL
tinyusdz-0.8.0rc6.dist-info/METADATA
tinyusdz-0.8.0rc6.dist-info/LICENSE
tinyusdz-0.8.0rc6.dist-info/RECORD
tinyusdz-0.8.0rc6.dist-info/top_level.txt
