Metadata-Version: 2.1
Name: tinyusdz
Version: 0.8.0rc6
Summary: UNKNOWN
Home-page: UNKNOWN
Author: Light Transport Entertainment Inc.
Author-email: syoyo@lighttransport.com, lighttransport.eth@mail3.me
License: MIT
Platform: UNKNOWN
License-File: LICENSE
